dwlog/__init__.py
dwlog/pandas.py
dwlog-0.1.1.dist-info/LICENSE
dwlog-0.1.1.dist-info/METADATA
dwlog-0.1.1.dist-info/WHEEL
dwlog-0.1.1.dist-info/RECORD
