Metadata-Version: 2.3
Name: dwlog
Version: 0.1.1
Summary: Logging functionalities for data wrangling in Python (pandas).
License: MIT
Author: Raffaele Mancuso
Author-email: raffaele.mancuso4@unibo.it
Requires-Python: >=3.8
Classifier: Development Status :: 3 - Alpha
Classifier: Environment :: Console
Classifier: Intended Audience :: Science/Research
Classifier: License :: OSI Approved :: BSD License
Classifier: Operating System :: OS Independent
Classifier: Programming Language :: Cython
Classifier: Programming Language :: Python
Classifier: Programming Language :: Python :: 3
Classifier: Programming Language :: Python :: 3 :: Only
Classifier: Programming Language :: Python :: 3.10
Classifier: Programming Language :: Python :: 3.11
Classifier: Programming Language :: Python :: 3.12
Classifier: Programming Language :: Python :: 3.13
Classifier: Topic :: Scientific/Engineering
Requires-Dist: pandas
Project-URL: Homepage, https://github.com/raffaem/dwlog
Project-URL: Issues, https://github.com/raffaem/dwlog/issues
